ffq/__init__.py
ffq/config.py
ffq/exceptions.py
ffq/ffq.py
ffq/main.py
ffq/utils.py
ffq-0.3.1.dist-info/LICENSE
ffq-0.3.1.dist-info/METADATA
ffq-0.3.1.dist-info/WHEEL
ffq-0.3.1.dist-info/entry_points.txt
ffq-0.3.1.dist-info/top_level.txt
ffq-0.3.1.dist-info/RECORD
