Metadata-Version: 2.1
Name: ffq
Version: 0.3.1
Summary: A command line tool that makes it easier to find sequencing data from SRA / GEO / ENCODE / ENA / EBI-EMBL / DDBJ / Biosample.
Home-page: https://github.com/pachterlab/ffq
Author: Kyung Hoi (Joseph) Min, Sina Booeshaghi, Ángel Gálvez Merchán
Author-email: phoenixter96@gmail.com, alisina@caltech.edu, agalvezm@caltech.edu
Maintainer: Pachter Lab
Maintainer-email: lpachter@caltech.edu
License: MIT
Platform: UNKNOWN
Classifier: Development Status :: 5 - Production/Stable
Classifier: Environment :: Console
Classifier: Intended Audience :: Science/Research
Classifier: License :: OSI Approved :: MIT License
Classifier: Operating System :: OS Independent
Classifier: Programming Language :: Python :: 3.6
Classifier: Programming Language :: Python :: 3.7
Classifier: Programming Language :: Python :: 3.8
Classifier: Programming Language :: Python :: 3.9
Classifier: Programming Language :: Python :: 3.10
Classifier: Topic :: Scientific/Engineering :: Bio-Informatics
Classifier: Topic :: Utilities
Requires-Python: >=3.6
